<?xml version="1.0" encoding="UTF-8"?>
<!DOCTYPE suite SYSTEM "http://testng.org/testng-1.0.dtd">
<suite name="Agency Positive Flow">
  <test verbose="2" name="LOGIN">
      
    <parameter name="testcase" value="AdminLogin"/>
    <classes>
      <class name="com.eBMS.app.testEngine.TestCaseEngine"/>
    </classes>
  </test>
  
  <test verbose="2" name="CUSTOMER_MASTER_ADD">
    <parameter name="testcase" value="CustomerMasterADD"/>
    <classes>
      <class name="com.eBMS.app.testEngine.TestCaseEngine"/>
    </classes>    
  </test> 
  
  <test verbose="2" name="CUSTOMER_MASTER_DELETE">
    <parameter name="testcase" value="CustomerMasterDEL"/>
    <classes>
      <class name="com.eBMS.app.testEngine.TestCaseEngine"/>
    </classes>    
  </test> 
  
  <test verbose="2" name="RATE_REQUEST_ADD">
    <parameter name="testcase" value="RateRequestADD"/>
    <classes>
      <class name="com.eBMS.app.testEngine.TestCaseEngine"/>
    </classes>
  </test>
    
  <test verbose="2" name="BookingADD">
    <parameter name="testcase" value="BookingADD"/>
    <classes>
      <class name="com.eBMS.app.testEngine.TestCaseEngine"/>
    </classes>
  </test>
  
  
</suite> <!-- Default suite -->
